[
    {
        "title": "The Bridge",
        "rating": "★★★★★",
        "price": "$$$",
        "imgsrcs": [
            "img/bridge/bridge-01.png",
            "img/bridge/bridge-02.png",
            "img/bridge/bridge-03.png",
            "img/bridge/bridge-04.png"
        ],
        "city": "Jakarta",
        "country": "Indonesia",
        "cuisine": "Italian",
        "review": "This burger is absolutely delicious with juicy meat and fresh ingredients."
    },
    {
        "title": "Katz's Delicatessen",
        "rating": "★★★★★",
        "price": "$$",
        "imgsrcs": [
            "img/katz/katz-01.png",
            "img/katz/katz-03.png",
            "img/katz/katz-04.png",
            "img/katz/katz-02.png",
            "img/katz/katz-05.png",
            "img/katz/katz-06.png"
        ],
        "city": "New York City",
        "country": "USA",
        "cuisine": "Jewish",
        "review": "This burger is absolutely delicious  with juicy meat and fresh ingredients. dhdesjnhejsnds with juicy meat and fresh ingredients. dhdesjnhejsnds with juicy meat and fresh ingredients. dhdesjnhejsndswith juicy meat and fresh ingredients. dhdesjnhejsnds"
    },
    {
        "title": "Zodiac Baresto",
        "rating": "★★★★☆",
        "price": "$$$",
        "imgsrcs": [
            "img/zodiac/zodiac-03.png",
            "img/zodiac/zodiac-04.png",
            "img/zodiac/zodiac-01.png",
            "img/zodiac/zodiac-02.png",
            "img/zodiac/zodiac-05.png",
            "img/zodiac/zodiac-06.png"
        ],
        "city": "Jakarta",
        "country": "Indonesia",
        "cuisine": "Fusian",
        "review": "This burger is absolutely delicious with juicy meat and fresh ingredients."
    },
    {
        "title": "The India",
        "rating": "★★★★☆",
        "price": "$$",
        "imgsrcs": [
            "img/india/india-01.png",
            "img/india/india-02.png",
            "img/india/india-03.png",
            "img/india/india-04.png"
        ],
        "city": "London",
        "country": "UK",
        "cuisine": "Indian",
        "review": "This burger is absolutely haha's delicious with juicy meat and fresh ingredients."
    },
    {
        "title": "Omoide Yokocho",
        "rating": "★★☆☆☆",
        "price": "$",
        "imgsrcs": [
            "img/omoide/omoide-01.png",
            "img/omoide/omoide-02.png",
            "img/omoide/omoide-03.png",
            "img/omoide/omoide-04.png"
        ],
        "city": "Tokyo",
        "country": "Japan",
        "cuisine": "Japanese",
        "review": "This burger is absolutely delicious with juicy meat and fresh ingredients."
    },
    {
        "title": "Ming's Seafood",
        "rating": "★★★★☆",
        "price": "$$",
        "imgsrcs": [
            "img/ming/ming-01.png",
            "img/ming/ming-02.png",
            "img/ming/ming-03.png",
            "img/ming/ming-04.png"
        ],
        "city": "Boston",
        "country": "USA",
        "cuisine": "Chinese",
        "review": "This burger is absolutely delicious with juicy meat and fresh ingredients."
    },
    {
        "title": "Dish",
        "rating": "★★☆☆☆",
        "price": "$$",
        "imgsrcs": [
            "lobster.png",
            "lobster.png"
        ],
        "city": "Singapore",
        "country": "Singapore",
        "cuisine": "Indian",
        "review": "This burger is absolutely delicious with juicy meat and fresh ingredients."
    },
    {
        "title": "Sushi by M",
        "rating": "★★★★☆",
        "price": "$$$",
        "imgsrcs": [
            "img/bym/bym-01.png",
            "img/bym/bym-02.png",
            "img/bym/bym-09.png",
            "img/bym/bym-04.png",
            "img/bym/bym-05.png",
            "img/bym/bym-06.png",
            "img/bym/bym-07.png",
            "img/bym/bym-08.png",
            "img/bym/bym-09.png",
            "img/bym/bym-10.png",
            "img/bym/bym-11.png",
            "img/bym/bym-12.png"
        ],
        "city": "New York City",
        "country": "USA",
        "cuisine": "Japanese",
        "review": "This burger is absolutely delicious with juicy meat and fresh ingredients."
    }
]